dephell_changelogs-0.0.1.dist-info/dependency_links.txt
dephell_changelogs-0.0.1.dist-info/entry_points.txt
dephell_changelogs-0.0.1.dist-info/METADATA
dephell_changelogs-0.0.1.dist-info/top_level.txt
dephell_changelogs-0.0.1.dist-info/WHEEL
dephell_changelogs/_cli.py
dephell_changelogs/__init__.py
dephell_changelogs/_parser.py
dephell_changelogs/__main__.py
dephell_changelogs/_finder.py
dephell_changelogs-0.0.1.dist-info/LICENSE
dephell_changelogs-0.0.1.dist-info/RECORD