Metadata-Version: 2.1
Name: dephell-changelogs
Version: 0.0.1
Summary: Find changelog for github repository, local dir, parse changelog
Home-Page: https://github.com/dephell/dephell_changelogs
Author: Gram (@orsinium)
Author-email: gram@orsinium.dev
Requires-Python: >=3.5
Classifier: Development Status :: 5 - Production/Stable
Classifier: Environment :: Console
Classifier: Intended Audience :: Developers
Classifier: License :: OSI Approved :: MIT License
Classifier: Programming Language :: Python :: 3.5
Classifier: Programming Language :: Python :: 3.6
Classifier: Programming Language :: Python :: 3.7
Classifier: Programming Language :: Python :: 3
Classifier: Programming Language :: Python
Classifier: Topic :: Software Development :: Libraries :: Python Modules
Requires-Dist: pytest; extra == "dev"
Requires-Dist: pytest-xdist; extra == "dev"
Requires-Dist: requests
Provides-Extra: dev
